voidrail/__init__.py
voidrail/__main__.py
voidrail/__version__.py
voidrail/client.py
voidrail/config.py
voidrail/echo/__init__.py
voidrail/echo/hello.py
voidrail/factory.py
voidrail-0.3.3.dist-info/LICENSE
voidrail-0.3.3.dist-info/METADATA
voidrail-0.3.3.dist-info/WHEEL
voidrail-0.3.3.dist-info/RECORD
