Metadata-Version: 2.3
Name: voidrail
Version: 0.3.3
Summary: 
Author: arcstep
Author-email: 43801@qq.com
Requires-Python: >=3.11,<4.0
Classifier: Programming Language :: Python :: 3
Classifier: Programming Language :: Python :: 3.11
Classifier: Programming Language :: Python :: 3.12
Classifier: Programming Language :: Python :: 3.13
Requires-Dist: async-timeout (>=5.0.1,<6.0.0)
Requires-Dist: celery (>=5.5.2,<6.0.0)
Requires-Dist: click (>=8.1.8,<9.0.0)
Requires-Dist: redis (>=6.0.0,<7.0.0)
